README.rst
setup.py
Flask_Uplink.egg-info/PKG-INFO
Flask_Uplink.egg-info/SOURCES.txt
Flask_Uplink.egg-info/dependency_links.txt
Flask_Uplink.egg-info/not-zip-safe
Flask_Uplink.egg-info/requires.txt
Flask_Uplink.egg-info/top_level.txt
flask_uplink/__init__.py
flask_uplink/uplink.py